Metadata-Version: 2.1
Name: papago.py
Version: 0.1.0
Summary: 파이썬 네이버 파파고 API
Home-page: https://github.com/Beta5051/papago.py
Author: Beta5051
Author-email: beta5051@gmail.com
License: UNKNOWN
Platform: UNKNOWN
